apiwrappers/__init__.py
apiwrappers/auth.py
apiwrappers/compat.py
apiwrappers/drivers/__init__.py
apiwrappers/drivers/aiohttp.py
apiwrappers/drivers/requests.py
apiwrappers/entities.py
apiwrappers/exceptions.py
apiwrappers/factories.py
apiwrappers/middleware/__init__.py
apiwrappers/middleware/auth.py
apiwrappers/middleware/base.py
apiwrappers/middleware/chain.py
apiwrappers/protocols.py
apiwrappers/py.typed
apiwrappers/shortcuts.py
apiwrappers/structures.py
apiwrappers/typedefs.py
apiwrappers/utils.py
apiwrappers/xfeatures.py
apiwrappers-0.5.0.dist-info/LICENSE
apiwrappers-0.5.0.dist-info/WHEEL
apiwrappers-0.5.0.dist-info/METADATA
apiwrappers-0.5.0.dist-info/RECORD
