Metadata-Version: 2.1
Name: apiwrappers
Version: 0.5.0
Summary: apiwrappers is a library for building API clients that work both with regular and async code
License: MIT
Keywords: api,wrapper,http,client
Author: Aleksei Maslakov
Author-email: lesha.maslakov@gmail.com
Requires-Python: >=3.7,<4.0
Classifier: Development Status :: 4 - Beta
Classifier: License :: OSI Approved :: MIT License
Classifier: Operating System :: OS Independent
Classifier: Programming Language :: Python :: 3
Classifier: Programming Language :: Python :: 3.10
Classifier: Programming Language :: Python :: 3.7
Classifier: Programming Language :: Python :: 3.8
Classifier: Programming Language :: Python :: 3.9
Classifier: Typing :: Typed
Provides-Extra: aiohttp
Provides-Extra: requests
Requires-Dist: aiohttp (>=3.6.2,<4.0.0); extra == "aiohttp"
Requires-Dist: certifi (>=2017.4.17); extra == "aiohttp"
Requires-Dist: requests (>=2.22.0,<3.0.0); extra == "requests"
Requires-Dist: typing-extensions (>=3.7.4,<4.0.0); python_version >= "3.7" and python_version < "3.8"
Project-URL: Documentation, https://apiwrappers.readthedocs.io/
